<?xml version="1.0" encoding="UTF-8"?>
<view_content> 
	
	<fieldline>
		<control id="bcXMLPathType" maskId="WSBuilderMask">
			<navigation name="wsbuilderUpdateUserGroupsOrUsers" type="standard" params=""/>
		</control>
	</fieldline>
	
	<fieldline height="25">
		<control id="bhUserGroup" maskId="WSBuilderMask"/>
		<control id="bhUser" maskId="WSBuilderMask"/>	
	</fieldline>
		
	<fieldline height="10"/>
	
	<fieldline>
		<control id="treeWorksheet" maskId="WSBuilderMask" width="300" height="300"/>
	</fieldline>
	
	<control id="bcOpenWorksheet" maskId="WSBuilderMask" position="396,323" width="98"/>
	
</view_content>